{
  "name": "SwiftDate",
  "version": "6.2.0",
  "summary": "The best way to deal with Dates & Time Zones in Swift",
  "homepage": "https://github.com/malcommac/SwiftDate.git",
  "license": {
    "type": "MIT",
    "file": "LICENSE"
  },
  "authors": {
    "Daniele Margutti": "hello@danielemargutti.com"
  },
  "social_media_url": "https://twitter.com/danielemargutti",
  "platforms": {
    "ios": "8.0"
  },
  "source": {
    "http": "http://localhost:8080/frameworks/SwiftDate/6.2.0/zip",
    "type": "zip"
  },
  "source_files": "Sources/**/*.swift",
  "frameworks": "Foundation",
  "swift_versions": [
    "5.0",
    "5.1"
  ],
  "resources": [
    "SwiftDate.framework/Resources/langs",
    "SwiftDate.framework/Versions/A/Resources/langs"
  ],
  "vendored_frameworks": "SwiftDate.framework",
  "description": "「   converted automatically by plugin cocoapods-imy-bin @厦门美柚 - slj    」",
  "swift_version": "5.1"
}
